Da_Ponz-4.0.4.dist-info/METADATA
Da_Ponz-4.0.4.dist-info/RECORD
Da_Ponz-4.0.4.dist-info/WHEEL
Da_Ponz-4.0.4.dist-info/top_level.txt
da_ponz/__init__.py
da_ponz/__main__.py
da_ponz/crypto_candle_collector.py
da_ponz/gdax/__init__.py
da_ponz/gdax/order_tools.py
da_ponz/strategies/__init__.py
da_ponz/strategies/augmented_dickey_fuller.py
da_ponz/strategies/common_functions.py
da_ponz/strategies/ltsm.py
da_ponz/strategies/multivariate_ltsm.py
da_ponz/strategies/testing.py
da_ponz/utilities/__init__.py
da_ponz/utilities/api_tools.py
da_ponz/utilities/graphing_tools.py
da_ponz/utilities/logging_tools.py
da_ponz/utilities/settings_tools.py
da_ponz/utilities/sql_tools.py
